gpboost/VERSION.txt
gpboost/__init__.py
gpboost/basic.py
gpboost/callback.py
gpboost/compat.py
gpboost/engine.py
gpboost/lib_gpboost.dll
gpboost/libpath.py
gpboost/plotting.py
gpboost/sklearn.py
gpboost-1.6.5.dist-info/licenses/LICENSE
gpboost-1.6.5.dist-info/METADATA
gpboost-1.6.5.dist-info/WHEEL
gpboost-1.6.5.dist-info/top_level.txt
gpboost-1.6.5.dist-info/RECORD
