Metadata-Version: 2.4
Name: gpboost
Version: 1.6.5
Summary: GPBoost Python Package
Home-page: https://github.com/fabsig/GPBoost
Maintainer: Fabio Sigrist
Maintainer-email: fabiosigrist@gmail.com
License: Apache License, Version 2.0, + see LICENSE file
Classifier: Development Status :: 5 - Production/Stable
Classifier: Intended Audience :: Science/Research
Classifier: License :: OSI Approved :: Apache Software License
Classifier: Natural Language :: English
Classifier: Operating System :: MacOS
Classifier: Operating System :: Microsoft :: Windows
Classifier: Operating System :: POSIX
Classifier: Operating System :: Unix
Classifier: Programming Language :: Python :: 3
Classifier: Programming Language :: Python :: 3.7
Classifier: Programming Language :: Python :: 3.8
Classifier: Programming Language :: Python :: 3.9
Classifier: Programming Language :: Python :: 3.10
Classifier: Programming Language :: Python :: 3.11
Classifier: Programming Language :: Python :: 3.12
Classifier: Programming Language :: Python :: 3.13
Classifier: Topic :: Scientific/Engineering :: Artificial Intelligence
Requires-Python: >=3.7
License-File: LICENSE
Requires-Dist: wheel
Requires-Dist: numpy
Requires-Dist: pandas
Requires-Dist: scipy
Requires-Dist: scikit-learn!=0.22.0
Requires-Dist: optuna
Provides-Extra: dask
Requires-Dist: dask[array]>=2.0.0; extra == "dask"
Requires-Dist: dask[dataframe]>=2.0.0; extra == "dask"
Requires-Dist: dask[distributed]>=2.0.0; extra == "dask"
Requires-Dist: pandas; extra == "dask"
Dynamic: classifier
Dynamic: description
Dynamic: description-content-type
Dynamic: home-page
Dynamic: license
Dynamic: license-file
Dynamic: maintainer
Dynamic: maintainer-email
Dynamic: provides-extra
Dynamic: requires-dist
Dynamic: requires-python
Dynamic: summary
